<DataObject comparison="Ordinal">
  <Section id="">
    <Subsections>
      <Section id="General">
        <Subsections />
        <Entries>
          <Entry key="ElapsedTime">
            <double>2.4419999999999997</double>
          </Entry>
          <Entry key="StartedAt">
            <dateTime>2020-09-19T13:34:50.9764168+03:00</dateTime>
          </Entry>
          <Entry key="EndedAt">
            <dateTime>2020-09-19T13:34:53.4179463+03:00</dateTime>
          </Entry>
          <Entry key="ReplayStatus">
            <LastReplayRunStatus>Passed</LastReplayRunStatus>
          </Entry>
          <Entry key="NumberOfReplayErrors">
            <int>0</int>
          </Entry>
          <Entry key="NumberOfReplayCriticalErrors">
            <int>0</int>
          </Entry>
          <Entry key="NumberOfCompilationErrors">
            <int>0</int>
          </Entry>
        </Entries>
      </Section>
    </Subsections>
    <Entries>
      <Entry key="Iterations">
        <int>1</int>
      </Entry>
    </Entries>
  </Section>
</DataObject>